{
  "$schema": "https://biomejs.dev/schemas/2.2.2/schema.json",
  "vcs": {
    "enabled": true,
    "clientKind": "git",
    "useIgnoreFile": true
  },
  "files": {
    "ignoreUnknown": false,
    "includes": [
      "**",
      "!**/.next",
      "!**/node_modules",
      "!**/out",
      "!**/dist",
      "!**/.vercel",
      "!src/generated/**"
    ]
  },
  "formatter": {
    "enabled": true,
    "formatWithErrors": false,
    "indentStyle": "space",
    "indentWidth": 2,
    "lineEnding": "lf",
    "lineWidth": 80,
    "attributePosition": "auto"
  },
  "assist": { "actions": { "source": { "organizeImports": "on" } } },
  "linter": {
    "enabled": true,
    "rules": {
      "recommended": true,
      "a11y": {
        "recommended": true
      },
      "complexity": {
        "recommended": true
      },
      "correctness": {
        "recommended": true
      },
      "nursery": {
        "recommended": false
      },
      "performance": {
        "recommended": true
      },
      "security": {
        "recommended": true
      },
      "style": {
        "recommended": true,
        "useImportType": "error"
      },
      "suspicious": {
        "recommended": true,
        "noUnknownAtRules": "off"
      }
    }
  },
  "javascript": {
    "formatter": {
      "jsxQuoteStyle": "double",
      "quoteProperties": "asNeeded",
      "trailingCommas": "all",
      "semicolons": "always",
      "arrowParentheses": "always",
      "bracketSpacing": true,
      "bracketSameLine": false,
      "quoteStyle": "double",
      "attributePosition": "auto"
    }
  },
  "json": {
    "formatter": {
      "enabled": true
    }
  }
}
